client_side_image_cropping/__init__.py
client_side_image_cropping/admin.py
client_side_image_cropping/apps.py
client_side_image_cropping/widgets.py
client_side_image_cropping/static/client_side_image_cropping/croppie-license.txt
client_side_image_cropping/static/client_side_image_cropping/croppie.css
client_side_image_cropping/static/client_side_image_cropping/croppie.min.js
client_side_image_cropping/static/client_side_image_cropping/cropping_widget.css
client_side_image_cropping/static/client_side_image_cropping/cropping_widget.js
client_side_image_cropping/templates/client-side_cropping_widget.html
django_client_side_image_cropping-0.1.dist-info/LICENSE
django_client_side_image_cropping-0.1.dist-info/METADATA
django_client_side_image_cropping-0.1.dist-info/WHEEL
django_client_side_image_cropping-0.1.dist-info/top_level.txt
django_client_side_image_cropping-0.1.dist-info/RECORD
