Metadata-Version: 2.1
Name: django-client-side-image-cropping
Version: 0.1
Summary: Widget for the Django ImageField that provides an interface for cropping the image client-side to a specific size.
Home-page: https://github.com/koendewit/django-client-side-image-cropping
Author: Koen De Wit
Author-email: koendewit@gmail.com
License: BSD-3-Clause
Platform: UNKNOWN
Classifier: Development Status :: 3 - Alpha
Classifier: Environment :: Web Environment
Classifier: Framework :: Django
Classifier: Framework :: Django :: 2.2
Classifier: Intended Audience :: Developers
Classifier: License :: OSI Approved :: BSD License
Classifier: Operating System :: OS Independent
Classifier: Programming Language :: Python
Classifier: Programming Language :: Python :: 3
Classifier: Programming Language :: Python :: 3 :: Only
Classifier: Programming Language :: Python :: 3.5
Classifier: Programming Language :: Python :: 3.6
Classifier: Programming Language :: Python :: 3.7
Classifier: Programming Language :: Python :: 3.8
Classifier: Topic :: Internet :: WWW/HTTP
Requires-Python: >=3.5
Requires-Dist: Django (>=2.2)
Requires-Dist: google-cloud-storage (>=1.25)
